beatdrop/__init__.py
beatdrop/art.py
beatdrop/entry_type_registry.py
beatdrop/exceptions.py
beatdrop/helpers.py
beatdrop/logger.py
beatdrop/messages.py
beatdrop/validators.py
beatdrop/entries/__init__.py
beatdrop/entries/crontab_entry.py
beatdrop/entries/crontab_tz_entry.py
beatdrop/entries/event_entry.py
beatdrop/entries/interval_entry.py
beatdrop/entries/schedule_entry.py
beatdrop/schedulers/__init__.py
beatdrop/schedulers/celery_redis_scheduler.py
beatdrop/schedulers/celery_scheduler.py
beatdrop/schedulers/celery_sql_scheduler.py
beatdrop/schedulers/mem_scheduler.py
beatdrop/schedulers/redis_scheduler.py
beatdrop/schedulers/rq_redis_scheduler.py
beatdrop/schedulers/rq_scheduler.py
beatdrop/schedulers/rq_sql_scheduler.py
beatdrop/schedulers/scheduler.py
beatdrop/schedulers/singleton_lock_scheduler.py
beatdrop/schedulers/sql_scheduler.py
beatdrop-0.1.0a9.dist-info/METADATA
beatdrop-0.1.0a9.dist-info/WHEEL
beatdrop-0.1.0a9.dist-info/top_level.txt
beatdrop-0.1.0a9.dist-info/RECORD
