Metadata-Version: 2.1
Name: beatdrop
Version: 0.1.0a9
Summary: Simplified, scalable task scheduling with typechecking.
Home-page: https://github.com/btemplep/beatdrop
Author: Brandon Temple Paul
Author-email: btemplepgit@gmail.com
License: MIT
Keywords: celery,beat,beatdrop,queue,redis,rq,schedule,scheduler,sql
Classifier: Development Status :: 3 - Alpha
Classifier: Framework :: Celery
Classifier: Framework :: FastAPI
Classifier: Framework :: Flask
Classifier: Intended Audience :: Developers
Classifier: License :: OSI Approved :: MIT License
Classifier: Natural Language :: English
Classifier: Operating System :: POSIX :: Linux
Classifier: Operating System :: Unix
Classifier: Programming Language :: Python :: 3
Classifier: Programming Language :: Python :: 3 :: Only
Classifier: Programming Language :: Python :: 3.7
Classifier: Programming Language :: Python :: 3.8
Classifier: Programming Language :: Python :: 3.9
Classifier: Programming Language :: Python :: 3.10
Classifier: Programming Language :: Python :: 3.11
Classifier: Programming Language :: Python :: 3.12
Classifier: Programming Language :: Python :: Implementation :: CPython
Classifier: Topic :: Software Development :: Libraries :: Python Modules
Classifier: Topic :: Internet
Requires-Dist: croniter
Requires-Dist: loguru
Requires-Dist: jsonpickle
Requires-Dist: pydantic <2
Requires-Dist: pytz
Provides-Extra: all
Requires-Dist: beatdrop[celery,redis,rq,sql] ; extra == 'all'
Provides-Extra: celery
Requires-Dist: celery ; extra == 'celery'
Provides-Extra: dev
Requires-Dist: build ; extra == 'dev'
Requires-Dist: coverage ; extra == 'dev'
Requires-Dist: nox ; extra == 'dev'
Requires-Dist: piccolo-theme ; extra == 'dev'
Requires-Dist: pytest ; extra == 'dev'
Requires-Dist: pytest-cov ; extra == 'dev'
Requires-Dist: redislite ; extra == 'dev'
Requires-Dist: sphinx ; extra == 'dev'
Requires-Dist: twine ; extra == 'dev'
Provides-Extra: redis
Requires-Dist: pottery ==3.0.0 ; extra == 'redis'
Requires-Dist: redis ; extra == 'redis'
Provides-Extra: rq
Requires-Dist: rq ; extra == 'rq'
Provides-Extra: sql
Requires-Dist: SQLAlchemy <2.0.0 ; extra == 'sql'
